snekdate/__init__.py
snekdate/snekdate.py
snekdate-0.0.4.dist-info/METADATA
snekdate-0.0.4.dist-info/WHEEL
snekdate-0.0.4.dist-info/top_level.txt
snekdate-0.0.4.dist-info/RECORD
