Metadata-Version: 2.1
Name: snekdate
Version: 0.0.4
Summary: A small, simple date tool library we use for our dashboards.
Home-page: https://github.com/ddsmit/snekdate/
Author: David Smit
Author-email: david.d.smit@gmail.com
License: MIT
Platform: UNKNOWN
Classifier: Intended Audience :: Developers
Classifier: License :: OSI Approved :: MIT License
Classifier: Operating System :: OS Independent
Classifier: Programming Language :: Python
Classifier: Programming Language :: Python :: 3.7
Classifier: Programming Language :: Python :: 3.8
Classifier: Programming Language :: Python :: 3.9
Classifier: Topic :: Software Development :: Libraries :: Python Modules
